LICENSE
MANIFEST.in
README.rst
setup.py
django_frontadmin.egg-info/PKG-INFO
django_frontadmin.egg-info/SOURCES.txt
django_frontadmin.egg-info/dependency_links.txt
django_frontadmin.egg-info/requires.txt
django_frontadmin.egg-info/top_level.txt
frontadmin/__init__.py
frontadmin/admin.py
frontadmin/apps.py
frontadmin/models.py
frontadmin/tests.py
frontadmin/urls.py
frontadmin/views.py
frontadmin/migrations/__init__.py
frontadmin/static/.DS_Store
frontadmin/static/frontadmin/.DS_Store
frontadmin/static/frontadmin/css/custom.css
frontadmin/static/frontadmin/css/forms.css
frontadmin/static/frontadmin/css/frontadmin.min.css
frontadmin/static/frontadmin/css/frontendadmin.css
frontadmin/static/frontadmin/css/widgets.css
frontadmin/static/frontadmin/img/AdminLTELogo.png
frontadmin/static/frontadmin/img/avatar.png
frontadmin/static/frontadmin/img/avatar2.png
frontadmin/static/frontadmin/img/avatar3.png
frontadmin/static/frontadmin/img/avatar4.png
frontadmin/static/frontadmin/img/avatar5.png
frontadmin/static/frontadmin/img/boxed-bg.jpg
frontadmin/static/frontadmin/img/boxed-bg.png
frontadmin/static/frontadmin/img/default-150x150.png
frontadmin/static/frontadmin/img/icons.png
frontadmin/static/frontadmin/img/logo.png
frontadmin/static/frontadmin/img/photo1.png
frontadmin/static/frontadmin/img/photo2.png
frontadmin/static/frontadmin/img/photo3.jpg
frontadmin/static/frontadmin/img/photo4.jpg
frontadmin/static/frontadmin/img/prod-1.jpg
frontadmin/static/frontadmin/img/prod-2.jpg
frontadmin/static/frontadmin/img/prod-3.jpg
frontadmin/static/frontadmin/img/prod-4.jpg
frontadmin/static/frontadmin/img/prod-5.jpg
frontadmin/static/frontadmin/img/user1-128x128.jpg
frontadmin/static/frontadmin/img/user2-160x160.jpg
frontadmin/static/frontadmin/img/user3-128x128.jpg
frontadmin/static/frontadmin/img/user4-128x128.jpg
frontadmin/static/frontadmin/img/user5-128x128.jpg
frontadmin/static/frontadmin/img/user6-128x128.jpg
frontadmin/static/frontadmin/img/user7-128x128.jpg
frontadmin/static/frontadmin/img/user8-128x128.jpg
frontadmin/static/frontadmin/img/credit/american-express.png
frontadmin/static/frontadmin/img/credit/cirrus.png
frontadmin/static/frontadmin/img/credit/mastercard.png
