Metadata-Version: 1.2
Name: django-frontadmin
Version: 4.0.7
Summary: Frontadmin is a Django app to conduct Web-based frontend theme.
Home-page: https://github.com/washim/django-frontadmin
Author: Washim Ahmed
Author-email: washim.ahmed@gmail.com
License: MIT
Platform: UNKNOWN
Requires-Python: >=3.6
